{
    "stamp":  "20260608-235929",
    "account":  "codex-live-v177-20260608-235929",
    "username":  "CodexLiveV177",
    "pid":  38136,
    "runLog":  "C:\\Users\\Administrator\\Downloads\\CustomServer\\logs\\live-medusa-direct-20260608-235929.log",
    "clientLog":  "C:\\Users\\Administrator\\Downloads\\CustomServer\\logs\\live-medusa-direct-client-20260608-235929.log",
    "clientErr":  "C:\\Users\\Administrator\\Downloads\\CustomServer\\logs\\live-medusa-direct-client-20260608-235929.err.log",
    "payload":  {
                    "gameId":  "matchmaking-20260608220002-6717",
                    "gameAuthId":  "03f7e3de725079a06cb7960dc1e67ce4",
                    "gameDns":  "ark.atomi23.de",
                    "wsPort":  7778,
                    "kcpPort":  7779,
                    "tcpPort":  7780,
                    "mapId":  4,
                    "levelId":  4,
                    "unityGameMode":  1
                },
    "serverRelease":  "medusa-v1711-runtime-cleanup",
    "medusaServerDll":  "232ABEE4D2EFBA343CF0C0ACCD2673476CE0B61DBBCCBAB19225E02F8231225A",
    "useLocalProxy":  false
}
